camunda_client/__init__.py
camunda_client/c8/__init__.py
camunda_client/c8/api/__init__.py
camunda_client/c8/api/job.py
camunda_client/c8/api/message.py
camunda_client/c8/api/process_instance.py
camunda_client/c8/api/signal.py
camunda_client/c8/api/topology.py
camunda_client/c8/auth/__init__.py
camunda_client/c8/auth/auth.py
camunda_client/c8/models/__init__.py
camunda_client/c8/models/camunda_headers.py
camunda_client/c8/models/job.py
camunda_client/c8/models/message.py
camunda_client/c8/models/process_instance.py
camunda_client/c8/models/signal.py
camunda_client/c8/models/topology.py
camunda_client/c8/worker/__init__.py
camunda_client/c8/worker/worker.py
camunda_client/config/__init__.py
camunda_client/config/lib_config.py
camunda_client/config/models.py
camunda_client/error/__init__.py
camunda_client/error/error_code.py
camunda_client/error/job_exception.py
camunda_client/error/service_exception.py
camunda_client/error/signature_exception.py
camunda_client/log/__init__.py
camunda_client/log/logger.py
camunda_client/utils/__init__.py
camunda_client/utils/base_model.py
c8_client-8.7.2.dist-info/LICENSE
c8_client-8.7.2.dist-info/METADATA
c8_client-8.7.2.dist-info/WHEEL
c8_client-8.7.2.dist-info/RECORD
